AUTHORS.rst
CHANGES.rst
LICENSE.txt
MANIFEST.in
README.rst
pyproject.toml
setup.cfg
setup.py
docs/Makefile
docs/conf.py
docs/genindex.rst
docs/index.rst
docs/typical_attributes.rst
docs/code_overview/exceptions.rst
docs/code_overview/other.rst
docs/code_overview/praw_models.rst
docs/code_overview/reddit_instance.rst
docs/code_overview/models/comment.rst
docs/code_overview/models/draft.rst
docs/code_overview/models/livethread.rst
docs/code_overview/models/liveupdate.rst
docs/code_overview/models/message.rst
docs/code_overview/models/modmailconversation.rst
docs/code_overview/models/more.rst
docs/code_overview/models/multireddit.rst
docs/code_overview/models/redditor.rst
docs/code_overview/models/submission.rst
docs/code_overview/models/subreddit.rst
docs/code_overview/models/wikipage.rst
docs/code_overview/other/auth.rst
docs/code_overview/other/base_mod_notes.rst
docs/code_overview/other/baselist.rst
docs/code_overview/other/button.rst
docs/code_overview/other/buttonwidget.rst
docs/code_overview/other/calendar.rst
docs/code_overview/other/calendarconfiguration.rst
docs/code_overview/other/collection.rst
docs/code_overview/other/collectionmoderation.rst
docs/code_overview/other/commentforest.rst
docs/code_overview/other/commenthelper.rst
docs/code_overview/other/commentmoderation.rst
docs/code_overview/other/communitylist.rst
docs/code_overview/other/config.rst
docs/code_overview/other/contributorrelationship.rst
docs/code_overview/other/customwidget.rst
docs/code_overview/other/domainlisting.rst
docs/code_overview/other/draftlist.rst
docs/code_overview/other/emoji.rst
docs/code_overview/other/fullnamemixin.rst
docs/code_overview/other/hover.rst
docs/code_overview/other/idcard.rst
docs/code_overview/other/image.rst
docs/code_overview/other/imagedata.rst
docs/code_overview/other/imagewidget.rst
docs/code_overview/other/inboxablemixin.rst
docs/code_overview/other/inlinegif.rst
docs/code_overview/other/inlineimage.rst
docs/code_overview/other/inlinemedia.rst
pbfaw.egg-info/PKG-INFO
pbfaw.egg-info/SOURCES.txt
pbfaw.egg-info/dependency_links.txt
pbfaw.egg-info/requires.txt
pbfaw.egg-info/top_level.txt
